{
  "type": "object",
  "properties": {
    "id": {
      "type": [
        "string",
        "null"
      ]
    },
    "name": {
      "type": [
        "string",
        "null"
      ]
    },
    "description": {
      "type": [
        "string",
        "null"
      ]
    },
    "field_type": {
      "type": [
        "string",
        "null"
      ]
    },
    "catalog_type_id": {
      "type": [
        "string",
        "null"
      ]
    },
    "created_at": {
      "type": [
        "string",
        "null"
      ],
      "format": "date-time"
    },
    "updated_at": {
      "type": [
        "string",
        "null"
      ],
      "format": "date-time"
    },
    "time_extracted": {
      "type": ["string"],
      "format": "date-time"
    }
  }
}